{
    "id": "29b27f4f-784c-4b77-8c56-b4aa248751c4",
    "source_id": "Geesebook1",
    "document_id": "29b27f4f-784c-4b77-8c56-b4aa248751c4",
    "genre": "",
    "festum": "",
    "dies": "",
    "textinitium": "Proprietas in personis unitas est",
    "rowstart": "5",
    "foliostart": "0207",
    "additionalData": {
        "Editor": "OMMR4all",
        "Endseite": "0207",
        "Endzeile": "6",
        "Melodie_Quelle": [
            "https://iiif-ls6.informatik.uni-wuerzburg.de/iiif/3/Geesebook1%2Ffolio_0207.jpg"
        ],
        "iiifs": [
            "https://iiif-ls6.informatik.uni-wuerzburg.de/iiif/3/Geesebook1%2Ffolio_0207.jpg"
        ],
        "manuscript": ""
    },
    "publish": null
}