{
    "kind": "RootContainer",
    "uuid": "493eb907-b630-4eb3-b20d-569f02a14ef5",
    "children": [
        {
            "kind": "FormteilContainer",
            "uuid": "0924b86c-b332-40bf-b050-5f8680977c26",
            "children": [
                {
                    "kind": "ZeileContainer",
                    "uuid": "9daf2c52-4ae2-45b9-8615-051ac27767da",
                    "children": [
                        {
                            "uuid": "d74cc9ce-0aa2-4b7c-92b9-3908ee7de0f8",
                            "kind": "Clef",
                            "focus": false,
                            "base": "F",
                            "octave": 4,
                            "shape": "F"
                        },
                        {
                            "uuid": "187748bf-0b36-4256-bf8d-b75340a01402",
                            "kind": "Syllable",
                            "text": "Ad",
                            "notes": {
                                "spaced": [
                                    {
                                        "nonSpaced": [
                                            {
                                                "grouped": [
                                                    {
                                                        "noteType": "Normal",
                                                        "base": "C",
                                                        "liquescent": false,
                                                        "octave": 4,
                                                        "focus": false,
                                                        "uuid": "e5beabfe-207f-4582-a5fb-c41846c76364"
                                                    }
                                                ]
                                            }
                                        ]
                                    }
                                ]
                            },
                            "syllableType": "Normal"
                        },
                        {
                            "uuid": "f6cf73e4-0c4b-4992-b7a8-8560a20601e7",
                            "kind": "Syllable",
                            "text": "do-",
                            "notes": {
                                "spaced": [
                                    {
                                        "nonSpaced": [
                                            {
                                                "grouped": [
                                                    {
                                                        "noteType": "Normal",
                                                        "base": "F",
                                                        "liquescent": false,
                                                        "octave": 4,
                                                        "focus": false,
                                                        "uuid": "49d80acd-85d8-499e-9eed-7829198e9d4d"
                                                    }
                                                ]
                                            },
                                            {
                                                "grouped": [
                                                    {
                                                        "noteType": "Normal",
                                                        "base": "F",
                                                        "liquescent": false,
                                                        "octave": 4,
                                                        "focus": false,
                                                        "uuid": "3022af1d-3b08-4481-8dc2-83792caf747b"
                                                    }
                                                ]
                                            }
                                        ]
                                    }
                                ]
                            },
                            "syllableType": "Normal"
                        },
                        {
                            "uuid": "3caa8d75-9444-4fd2-b495-7f8b9e6e3114",
                            "kind": "Syllable",
                            "text": "mi-",
                            "notes": {
                                "spaced": [
                                    {
                                        "nonSpaced": [
                                            {
                                                "grouped": [
                                                    {
                                                        "noteType": "Normal",
                                                        "base": "F",
                                                        "liquescent": false,
                                                        "octave": 4,
                                                        "focus": false,
                                                        "uuid": "c7eafa51-1225-4d76-bdd2-da75ab5a8a9d"
                                                    },
                                                    {
                                                        "noteType": "Normal",
                                                        "base": "G",
                                                        "liquescent": false,
                                                        "octave": 4,
                                                        "focus": false,
                                                        "uuid": "0ed928c6-0376-4f7d-a570-37f0b05d75ea"
                                                    },
                                                    {
                                                        "noteType": "Normal",
                                                        "base": "F",
                                                        "liquescent": false,
                                                        "octave": 4,
                                                        "focus": false,
                                                        "uuid": "0a3d71b8-5969-402a-93fb-4a5d1e1eccd1"
                                                    }
                                                ]
                                            },
                                            {
                                                "grouped": [
                                                    {
                                                        "noteType": "Normal",
                                                        "base": "F",
                                                        "liquescent": false,
                                                        "octave": 4,
                                                        "focus": false,
                                                        "uuid": "1bfcb5e0-9252-4437-aadd-d8af7f266e99"
                                                    }
                                                ]
                                            },
                                            {
                                                "grouped": [
                                                    {
                                                        "noteType": "Normal",
                                                        "base": "F",
                                                        "liquescent": false,
                                                        "octave": 4,
                                                        "focus": false,
                                                        "uuid": "2b41ce5a-8a57-4574-b1b9-df3d13bcd8c1"
                                                    }
                                                ]
                                            }
                                        ]
                                    }
                                ]
                            },
                            "syllableType": "Normal"
                        },
                        {
                            "uuid": "0692fec8-3b19-4cb3-9aab-4296cb5052d8",
                            "kind": "Syllable",
                            "text": "num",
                            "notes": {
                                "spaced": [
                                    {
                                        "nonSpaced": [
                                            {
                                                "grouped": [
                                                    {
                                                        "noteType": "Normal",
                                                        "base": "F",
                                                        "liquescent": false,
                                                        "octave": 4,
                                                        "focus": false,
                                                        "uuid": "41ff20a3-b92b-42ae-a4ba-c6c8232d06a1"
                                                    },
                                                    {
                                                        "noteType": "Normal",
                                                        "base": "D",
                                                        "liquescent": false,
                                                        "octave": 4,
                                                        "focus": false,
                                                        "uuid": "8821598e-49e4-46dc-bfd7-dfc888fb949a"
                                                    }
                                                ]
                                            },
                                            {
                                                "grouped": [
                                                    {
                                                        "noteType": "Normal",
                                                        "base": "E",
                                                        "liquescent": false,
                                                        "octave": 4,
                                                        "focus": false,
                                                        "uuid": "fe8fa3be-8df0-4610-b0ce-469a01021bfc"
                                                    }
                                                ]
                                            },
                                            {
                                                "grouped": [
                                                    {
                                                        "noteType": "Normal",
                                                        "base": "F",
                                                        "liquescent": false,
                                                        "octave": 4,
                                                        "focus": false,
                                                        "uuid": "cfa08886-e5f4-4727-b6e5-1d9b2350b8b8"
                                                    },
                                                    {
                                                        "noteType": "Normal",
                                                        "base": "A",
                                                        "liquescent": false,
                                                        "octave": 4,
                                                        "focus": false,
                                                        "uuid": "f1113533-8b84-477c-b933-c5e1534d6881"
                                                    },
                                                    {
                                                        "noteType": "Normal",
                                                        "base": "E",
                                                        "liquescent": false,
                                                        "octave": 4,
                                                        "focus": false,
                                                        "uuid": "3289d1ef-6d5e-4ea7-8ba8-e35e06992e97"
                                                    }
                                                ]
                                            },
                                            {
                                                "grouped": [
                                                    {
                                                        "noteType": "Normal",
                                                        "base": "F",
                                                        "liquescent": false,
                                                        "octave": 4,
                                                        "focus": false,
                                                        "uuid": "0d30bb3f-411c-47f9-87a2-65f3dbfc53ca"
                                                    },
                                                    {
                                                        "noteType": "Normal",
                                                        "base": "G",
                                                        "liquescent": false,
                                                        "octave": 4,
                                                        "focus": false,
                                                        "uuid": "dcf0f357-1009-4061-b8bf-59ee7f6dce47"
                                                    },
                                                    {
                                                        "noteType": "Normal",
                                                        "base": "D",
                                                        "liquescent": false,
                                                        "octave": 4,
                                                        "focus": false,
                                                        "uuid": "d3a72ec6-b72b-4a33-aa97-f0da2d6105b5"
                                                    }
                                                ]
                                            },
                                            {
                                                "grouped": [
                                                    {
                                                        "noteType": "Normal",
                                                        "base": "F",
                                                        "liquescent": false,
                                                        "octave": 4,
                                                        "focus": false,
                                                        "uuid": "88e7183f-6280-446f-9aff-dbb1d7b5e56c"
                                                    },
                                                    {
                                                        "noteType": "Normal",
                                                        "base": "D",
                                                        "liquescent": false,
                                                        "octave": 4,
                                                        "focus": false,
                                                        "uuid": "6986523c-5b96-47cd-a316-e337de6a27fb"
                                                    }
                                                ]
                                            },
                                            {
                                                "grouped": [
                                                    {
                                                        "noteType": "Normal",
                                                        "base": "D",
                                                        "liquescent": false,
                                                        "octave": 4,
                                                        "focus": false,
                                                        "uuid": "4097eaf8-20ad-470f-b851-83d89fc5dcbe"
                                                    },
                                                    {
                                                        "noteType": "Normal",
                                                        "base": "C",
                                                        "liquescent": false,
                                                        "octave": 4,
                                                        "focus": false,
                                                        "uuid": "1ddc20d0-c170-4a57-821e-2b28b1a5e2e5"
                                                    }
                                                ]
                                            }
                                        ]
                                    }
                                ]
                            },
                            "syllableType": "Normal"
                        },
                        {
                            "uuid": "fda0de14-4434-4570-a320-8700a6490787",
                            "kind": "Syllable",
                            "text": "cum",
                            "notes": {
                                "spaced": [
                                    {
                                        "nonSpaced": [
                                            {
                                                "grouped": [
                                                    {
                                                        "noteType": "Normal",
                                                        "base": "F",
                                                        "liquescent": false,
                                                        "octave": 4,
                                                        "focus": false,
                                                        "uuid": "1b8030d5-0b60-47bf-997e-09ef573219a6"
                                                    }
                                                ]
                                            }
                                        ]
                                    }
                                ]
                            },
                            "syllableType": "Normal"
                        },
                        {
                            "uuid": "438f6d9f-237b-4f82-9d2a-33e94311d60c",
                            "kind": "Syllable",
                            "text": "tri",
                            "notes": {
                                "spaced": [
                                    {
                                        "nonSpaced": [
                                            {
                                                "grouped": [
                                                    {
                                                        "noteType": "Normal",
                                                        "base": "F",
                                                        "liquescent": false,
                                                        "octave": 4,
                                                        "focus": false,
                                                        "uuid": "233344e8-e0cb-469c-8c31-9d9d629e9889"
                                                    }
                                                ]
                                            }
                                        ]
                                    }
                                ]
                            },
                            "syllableType": "Normal"
                        }
                    ]
                },
                {
                    "kind": "ZeileContainer",
                    "uuid": "9e7ae123-3c91-45d6-8b3a-13ea1b99736a",
                    "children": [
                        {
                            "uuid": "5c37af8d-a00f-4e0b-9a6a-2f7a688774e6",
                            "kind": "Clef",
                            "focus": false,
                            "base": "F",
                            "octave": 4,
                            "shape": "F"
                        },
                        {
                            "uuid": "7a38c24d-59ec-466c-80bb-fa99a884af47",
                            "kind": "Clef",
                            "focus": false,
                            "base": "F",
                            "octave": 4,
                            "shape": "F"
                        },
                        {
                            "uuid": "bcd850c1-483b-493a-9b67-d619736212f1",
                            "kind": "Syllable",
                            "text": "bu-",
                            "notes": {
                                "spaced": [
                                    {
                                        "nonSpaced": [
                                            {
                                                "grouped": [
                                                    {
                                                        "noteType": "Normal",
                                                        "base": "A",
                                                        "liquescent": false,
                                                        "octave": 4,
                                                        "focus": false,
                                                        "uuid": "4ac6f9e3-5fb6-4793-8abe-0dd294937dd2"
                                                    }
                                                ]
                                            }
                                        ]
                                    }
                                ]
                            },
                            "syllableType": "Normal"
                        },
                        {
                            "uuid": "f4cdd221-cc6d-4f38-bf31-86c2032e7f51",
                            "kind": "Syllable",
                            "text": "la-",
                            "notes": {
                                "spaced": [
                                    {
                                        "nonSpaced": [
                                            {
                                                "grouped": [
                                                    {
                                                        "noteType": "Normal",
                                                        "base": "C",
                                                        "liquescent": false,
                                                        "octave": 5,
                                                        "focus": false,
                                                        "uuid": "8abc856c-118b-4373-91af-42b4391e50e0"
                                                    },
                                                    {
                                                        "noteType": "Normal",
                                                        "base": "A",
                                                        "liquescent": false,
                                                        "octave": 4,
                                                        "focus": false,
                                                        "uuid": "2b6b4534-0ec0-4fbe-8f5c-b7a2e44cef2f"
                                                    }
                                                ]
                                            },
                                            {
                                                "grouped": [
                                                    {
                                                        "noteType": "Normal",
                                                        "base": "C",
                                                        "liquescent": false,
                                                        "octave": 5,
                                                        "focus": false,
                                                        "uuid": "75f42474-40b0-4695-abb6-72ba92a04f48"
                                                    }
                                                ]
                                            },
                                            {
                                                "grouped": [
                                                    {
                                                        "noteType": "Normal",
                                                        "base": "C",
                                                        "liquescent": false,
                                                        "octave": 5,
                                                        "focus": false,
                                                        "uuid": "a3756388-4a87-4b42-9946-974b171fc0dd"
                                                    }
                                                ]
                                            }
                                        ]
                                    }
                                ]
                            },
                            "syllableType": "Normal"
                        },
                        {
                            "uuid": "4864b9aa-8298-4f8c-8f4e-9bbaa9872bcd",
                            "kind": "Syllable",
                            "text": "rer",
                            "notes": {
                                "spaced": [
                                    {
                                        "nonSpaced": [
                                            {
                                                "grouped": [
                                                    {
                                                        "noteType": "Normal",
                                                        "base": "C",
                                                        "liquescent": false,
                                                        "octave": 5,
                                                        "focus": false,
                                                        "uuid": "6e35d749-3455-4c52-ada7-15e6130f9f97"
                                                    }
                                                ]
                                            }
                                        ]
                                    }
                                ]
                            },
                            "syllableType": "Normal"
                        },
                        {
                            "uuid": "a250e1cd-58c7-4f53-821a-903a623728e9",
                            "kind": "Syllable",
                            "text": "cla-",
                            "notes": {
                                "spaced": [
                                    {
                                        "nonSpaced": [
                                            {
                                                "grouped": [
                                                    {
                                                        "noteType": "Normal",
                                                        "base": "C",
                                                        "liquescent": false,
                                                        "octave": 5,
                                                        "focus": false,
                                                        "uuid": "b0bd2d24-05a2-4564-913e-c6ff2cc3d020"
                                                    }
                                                ]
                                            }
                                        ]
                                    }
                                ]
                            },
                            "syllableType": "Normal"
                        },
                        {
                            "uuid": "8d457084-6298-41e5-8ab5-8926876a20ad",
                            "kind": "Syllable",
                            "text": "ma-",
                            "notes": {
                                "spaced": [
                                    {
                                        "nonSpaced": [
                                            {
                                                "grouped": [
                                                    {
                                                        "noteType": "Normal",
                                                        "base": "D",
                                                        "liquescent": false,
                                                        "octave": 5,
                                                        "focus": false,
                                                        "uuid": "c040ae71-e986-4cb4-8b9d-b19c6e078ca8"
                                                    },
                                                    {
                                                        "noteType": "Normal",
                                                        "base": "C",
                                                        "liquescent": false,
                                                        "octave": 5,
                                                        "focus": false,
                                                        "uuid": "73bd84ed-d693-4c04-95ed-5268527cb6de"
                                                    }
                                                ]
                                            },
                                            {
                                                "grouped": [
                                                    {
                                                        "noteType": "Normal",
                                                        "base": "C",
                                                        "liquescent": false,
                                                        "octave": 5,
                                                        "focus": false,
                                                        "uuid": "517c2ddc-139f-44d5-a799-b9e5429ff571"
                                                    }
                                                ]
                                            },
                                            {
                                                "grouped": [
                                                    {
                                                        "noteType": "Normal",
                                                        "base": "C",
                                                        "liquescent": false,
                                                        "octave": 5,
                                                        "focus": false,
                                                        "uuid": "65421c21-fed0-48d5-8af7-2f4b0f1d557b"
                                                    }
                                                ]
                                            },
                                            {
                                                "grouped": [
                                                    {
                                                        "noteType": "Normal",
                                                        "base": "B",
                                                        "liquescent": false,
                                                        "octave": 4,
                                                        "focus": false,
                                                        "uuid": "dc9ae908-4958-4ba8-b07d-9437bf51bb48"
                                                    }
                                                ]
                                            },
                                            {
                                                "grouped": [
                                                    {
                                                        "noteType": "Normal",
                                                        "base": "A",
                                                        "liquescent": false,
                                                        "octave": 4,
                                                        "focus": false,
                                                        "uuid": "7e3a38b6-a681-4b25-acb3-d38ce8226643"
                                                    },
                                                    {
                                                        "noteType": "Normal",
                                                        "base": "D",
                                                        "liquescent": false,
                                                        "octave": 5,
                                                        "focus": false,
                                                        "uuid": "399634f2-9a02-4d7b-a602-90f373e92c8c"
                                                    },
                                                    {
                                                        "noteType": "Normal",
                                                        "base": "C",
                                                        "liquescent": false,
                                                        "octave": 5,
                                                        "focus": false,
                                                        "uuid": "120ace6a-1d23-4463-9993-1f3158deafd1"
                                                    }
                                                ]
                                            },
                                            {
                                                "grouped": [
                                                    {
                                                        "noteType": "Normal",
                                                        "base": "C",
                                                        "liquescent": false,
                                                        "octave": 5,
                                                        "focus": false,
                                                        "uuid": "3153f89b-3c00-477d-bc53-2e27362b458b"
                                                    }
                                                ]
                                            },
                                            {
                                                "grouped": [
                                                    {
                                                        "noteType": "Normal",
                                                        "base": "C",
                                                        "liquescent": false,
                                                        "octave": 5,
                                                        "focus": false,
                                                        "uuid": "c34e9410-7c51-4ce6-8a15-1cbbcee01a49"
                                                    }
                                                ]
                                            },
                                            {
                                                "grouped": [
                                                    {
                                                        "noteType": "Normal",
                                                        "base": "C",
                                                        "liquescent": false,
                                                        "octave": 5,
                                                        "focus": false,
                                                        "uuid": "f4a27a33-1091-4395-b0d3-15002eee0737"
                                                    }
                                                ]
                                            },
                                            {
                                                "grouped": [
                                                    {
                                                        "noteType": "Normal",
                                                        "base": "A",
                                                        "liquescent": false,
                                                        "octave": 4,
                                                        "focus": false,
                                                        "uuid": "8b921d34-db1a-4ed9-ba95-7e5fa75509c0"
                                                    }
                                                ]
                                            },
                                            {
                                                "grouped": [
                                                    {
                                                        "noteType": "Normal",
                                                        "base": "G",
                                                        "liquescent": false,
                                                        "octave": 4,
                                                        "focus": false,
                                                        "uuid": "177251db-d4a1-4ee2-9f5e-67835708cea5"
                                                    },
                                                    {
                                                        "noteType": "Normal",
                                                        "base": "A",
                                                        "liquescent": false,
                                                        "octave": 4,
                                                        "focus": false,
                                                        "uuid": "56e40aa8-a39a-4b33-87b6-cef190c93641"
                                                    },
                                                    {
                                                        "noteType": "Normal",
                                                        "base": "G",
                                                        "liquescent": false,
                                                        "octave": 4,
                                                        "focus": false,
                                                        "uuid": "a299433b-c67d-4c61-b90c-f1a5f070eb9a"
                                                    }
                                                ]
                                            },
                                            {
                                                "grouped": [
                                                    {
                                                        "noteType": "Normal",
                                                        "base": "A",
                                                        "liquescent": false,
                                                        "octave": 4,
                                                        "focus": false,
                                                        "uuid": "2b6627c9-c9cf-4250-a317-984942c26ca5"
                                                    }
                                                ]
                                            },
                                            {
                                                "grouped": [
                                                    {
                                                        "noteType": "Normal",
                                                        "base": "C",
                                                        "liquescent": false,
                                                        "octave": 5,
                                                        "focus": false,
                                                        "uuid": "00358c48-8bca-4908-832b-735ab14f9988"
                                                    }
                                                ]
                                            },
                                            {
                                                "grouped": [
                                                    {
                                                        "noteType": "Normal",
                                                        "base": "C",
                                                        "liquescent": false,
                                                        "octave": 5,
                                                        "focus": false,
                                                        "uuid": "6580b158-3b41-4fab-9116-3ea9c19a14fc"
                                                    },
                                                    {
                                                        "noteType": "Normal",
                                                        "base": "D",
                                                        "liquescent": false,
                                                        "octave": 5,
                                                        "focus": false,
                                                        "uuid": "662578fb-af16-41fe-8a81-e64a28f35685"
                                                    }
                                                ]
                                            },
                                            {
                                                "grouped": [
                                                    {
                                                        "noteType": "Normal",
                                                        "base": "C",
                                                        "liquescent": false,
                                                        "octave": 5,
                                                        "focus": false,
                                                        "uuid": "37d1068e-9e1a-4b7d-8172-32a0bbaae1fb"
                                                    }
                                                ]
                                            },
                                            {
                                                "grouped": [
                                                    {
                                                        "noteType": "Normal",
                                                        "base": "B",
                                                        "liquescent": false,
                                                        "octave": 4,
                                                        "focus": false,
                                                        "uuid": "2c4373a5-2cc8-4c98-abea-e397a36233f2"
                                                    }
                                                ]
                                            }
                                        ]
                                    }
                                ]
                            },
                            "syllableType": "Normal"
                        },
                        {
                            "uuid": "5f8873a9-0376-4374-b07f-67a3a379a679",
                            "kind": "Syllable",
                            "text": "vi",
                            "notes": {
                                "spaced": [
                                    {
                                        "nonSpaced": [
                                            {
                                                "grouped": [
                                                    {
                                                        "noteType": "Normal",
                                                        "base": "C",
                                                        "liquescent": false,
                                                        "octave": 5,
                                                        "focus": false,
                                                        "uuid": "2d311390-28b8-45a3-b8b6-ea27e61b4401"
                                                    },
                                                    {
                                                        "noteType": "Normal",
                                                        "base": "B",
                                                        "liquescent": false,
                                                        "octave": 4,
                                                        "focus": false,
                                                        "uuid": "e527496c-cbd1-4b95-87a6-25c5e88e782d"
                                                    }
                                                ]
                                            }
                                        ]
                                    }
                                ]
                            },
                            "syllableType": "Normal"
                        },
                        {
                            "uuid": "c340a5ff-0044-4cb3-99f9-e579d311a05f",
                            "kind": "Syllable",
                            "text": "et",
                            "notes": {
                                "spaced": [
                                    {
                                        "nonSpaced": [
                                            {
                                                "grouped": [
                                                    {
                                                        "noteType": "Normal",
                                                        "base": "A",
                                                        "liquescent": false,
                                                        "octave": 4,
                                                        "focus": false,
                                                        "uuid": "12899fb9-c061-4827-a31b-15ccc6cb6f0b"
                                                    }
                                                ]
                                            }
                                        ]
                                    }
                                ]
                            },
                            "syllableType": "Normal"
                        }
                    ]
                },
                {
                    "kind": "ZeileContainer",
                    "uuid": "9f4cf84d-80e5-4c00-aa1e-89c4c5b6f8b5",
                    "children": [
                        {
                            "uuid": "569e0c66-0fbe-4250-a13f-6a9bc009b0c8",
                            "kind": "Clef",
                            "focus": false,
                            "base": "C",
                            "octave": 5,
                            "shape": "C"
                        },
                        {
                            "uuid": "48eb89ac-798a-4fc4-97db-8d5bc77837f3",
                            "kind": "Clef",
                            "focus": false,
                            "base": "F",
                            "octave": 4,
                            "shape": "F"
                        },
                        {
                            "uuid": "036fc806-8a22-41c3-b111-bdba6184268a",
                            "kind": "Clef",
                            "focus": false,
                            "base": "C",
                            "octave": 5,
                            "shape": "C"
                        },
                        {
                            "uuid": "7160fe98-cf95-4065-beb1-10eeaac45d05",
                            "kind": "Clef",
                            "focus": false,
                            "base": "F",
                            "octave": 4,
                            "shape": "F"
                        },
                        {
                            "uuid": "9e17b793-06a3-4ddc-83be-3b679a18fd00",
                            "kind": "Syllable",
                            "text": "ex-",
                            "notes": {
                                "spaced": [
                                    {
                                        "nonSpaced": [
                                            {
                                                "grouped": [
                                                    {
                                                        "noteType": "Normal",
                                                        "base": "A",
                                                        "liquescent": false,
                                                        "octave": 4,
                                                        "focus": false,
                                                        "uuid": "e267d257-ce80-4092-95b5-8ed1980f15bf"
                                                    },
                                                    {
                                                        "noteType": "Normal",
                                                        "base": "C",
                                                        "liquescent": false,
                                                        "octave": 5,
                                                        "focus": false,
                                                        "uuid": "bda068c9-59f0-4e59-8cd8-b633ec307b20"
                                                    }
                                                ]
                                            },
                                            {
                                                "grouped": [
                                                    {
                                                        "noteType": "Normal",
                                                        "base": "D",
                                                        "liquescent": false,
                                                        "octave": 5,
                                                        "focus": false,
                                                        "uuid": "aee10c6e-3913-4a94-adcf-2d76825338ca"
                                                    }
                                                ]
                                            }
                                        ]
                                    }
                                ]
                            },
                            "syllableType": "Normal"
                        },
                        {
                            "uuid": "96564ac1-dbc7-4b1a-9c78-769f97ce7e50",
                            "kind": "Syllable",
                            "text": "au-",
                            "notes": {
                                "spaced": [
                                    {
                                        "nonSpaced": [
                                            {
                                                "grouped": [
                                                    {
                                                        "noteType": "Normal",
                                                        "base": "C",
                                                        "liquescent": false,
                                                        "octave": 5,
                                                        "focus": false,
                                                        "uuid": "e2170353-e3f8-4a74-ae18-3d9e2fcaa59a"
                                                    }
                                                ]
                                            }
                                        ]
                                    }
                                ]
                            },
                            "syllableType": "Normal"
                        },
                        {
                            "uuid": "6e986077-ae4f-49f0-9b79-b99556b502e7",
                            "kind": "Syllable",
                            "text": "di-",
                            "notes": {
                                "spaced": [
                                    {
                                        "nonSpaced": [
                                            {
                                                "grouped": [
                                                    {
                                                        "noteType": "Normal",
                                                        "base": "A",
                                                        "liquescent": false,
                                                        "octave": 4,
                                                        "focus": false,
                                                        "uuid": "ca4f5621-f58c-44ff-82c9-3e889b1be36b"
                                                    },
                                                    {
                                                        "noteType": "Normal",
                                                        "base": "C",
                                                        "liquescent": false,
                                                        "octave": 5,
                                                        "focus": false,
                                                        "uuid": "49cb1709-71c7-42cf-9ee7-b95df54caeff"
                                                    }
                                                ]
                                            },
                                            {
                                                "grouped": [
                                                    {
                                                        "noteType": "Normal",
                                                        "base": "C",
                                                        "liquescent": false,
                                                        "octave": 5,
                                                        "focus": false,
                                                        "uuid": "2e2a7039-0558-4d73-b38a-92b973edaa6d"
                                                    },
                                                    {
                                                        "noteType": "Normal",
                                                        "base": "G",
                                                        "liquescent": false,
                                                        "octave": 4,
                                                        "focus": false,
                                                        "uuid": "9c2057f1-0a13-4c60-b3c9-7580006b9cd0"
                                                    }
                                                ]
                                            },
                                            {
                                                "grouped": [
                                                    {
                                                        "noteType": "Normal",
                                                        "base": "A",
                                                        "liquescent": false,
                                                        "octave": 4,
                                                        "focus": false,
                                                        "uuid": "317ed859-1df3-4980-8a40-4c76e6d35882"
                                                    }
                                                ]
                                            }
                                        ]
                                    }
                                ]
                            },
                            "syllableType": "Normal"
                        },
                        {
                            "uuid": "4cfcec17-cb78-4db0-99ba-c29f9f42546a",
                            "kind": "Syllable",
                            "text": "vit",
                            "notes": {
                                "spaced": [
                                    {
                                        "nonSpaced": [
                                            {
                                                "grouped": [
                                                    {
                                                        "noteType": "Normal",
                                                        "base": "F",
                                                        "liquescent": false,
                                                        "octave": 4,
                                                        "focus": false,
                                                        "uuid": "4c025905-4db7-453b-b108-89ee81546a04"
                                                    },
                                                    {
                                                        "noteType": "Normal",
                                                        "base": "G",
                                                        "liquescent": false,
                                                        "octave": 4,
                                                        "focus": false,
                                                        "uuid": "e9d5e315-a0ee-4192-b76a-49ce5d496ceb"
                                                    }
                                                ]
                                            }
                                        ]
                                    }
                                ]
                            },
                            "syllableType": "Normal"
                        },
                        {
                            "uuid": "e208b345-3dff-4abe-a0cc-11c6d644b6c7",
                            "kind": "Syllable",
                            "text": "me",
                            "notes": {
                                "spaced": [
                                    {
                                        "nonSpaced": [
                                            {
                                                "grouped": [
                                                    {
                                                        "noteType": "Normal",
                                                        "base": "F",
                                                        "liquescent": false,
                                                        "octave": 4,
                                                        "focus": false,
                                                        "uuid": "3852befb-e780-498e-8667-b654073aec5a"
                                                    }
                                                ]
                                            },
                                            {
                                                "grouped": [
                                                    {
                                                        "noteType": "Normal",
                                                        "base": "G",
                                                        "liquescent": false,
                                                        "octave": 4,
                                                        "focus": false,
                                                        "uuid": "e2375e69-1a28-4d07-8948-3baff8488058"
                                                    },
                                                    {
                                                        "noteType": "Normal",
                                                        "base": "A",
                                                        "liquescent": false,
                                                        "octave": 4,
                                                        "focus": false,
                                                        "uuid": "0b8f5073-7b2b-4bfd-97f7-8679904719ab"
                                                    }
                                                ]
                                            },
                                            {
                                                "grouped": [
                                                    {
                                                        "noteType": "Normal",
                                                        "base": "C",
                                                        "liquescent": false,
                                                        "octave": 5,
                                                        "focus": false,
                                                        "uuid": "e9828ce5-4560-430d-9833-965f92ef158c"
                                                    }
                                                ]
                                            },
                                            {
                                                "grouped": [
                                                    {
                                                        "noteType": "Normal",
                                                        "base": "C",
                                                        "liquescent": false,
                                                        "octave": 5,
                                                        "focus": false,
                                                        "uuid": "458dec34-3668-4a30-ae37-ebf90bc0b63a"
                                                    }
                                                ]
                                            },
                                            {
                                                "grouped": [
                                                    {
                                                        "noteType": "Normal",
                                                        "base": "D",
                                                        "liquescent": false,
                                                        "octave": 5,
                                                        "focus": false,
                                                        "uuid": "edf448ba-3538-45c8-b6dc-65493bfacd21"
                                                    },
                                                    {
                                                        "noteType": "Normal",
                                                        "base": "E",
                                                        "liquescent": false,
                                                        "octave": 5,
                                                        "focus": false,
                                                        "uuid": "b44973c7-3302-4e51-83c2-9972d272bcd9"
                                                    }
                                                ]
                                            },
                                            {
                                                "grouped": [
                                                    {
                                                        "noteType": "Normal",
                                                        "base": "C",
                                                        "liquescent": false,
                                                        "octave": 5,
                                                        "focus": false,
                                                        "uuid": "4aa8ed2c-4bba-4f3d-906b-8882d3ef4514"
                                                    }
                                                ]
                                            },
                                            {
                                                "grouped": [
                                                    {
                                                        "noteType": "Normal",
                                                        "base": "A",
                                                        "liquescent": false,
                                                        "octave": 4,
                                                        "focus": false,
                                                        "uuid": "a4817b96-6ffe-4559-bacd-a7eb78530a90"
                                                    }
                                                ]
                                            },
                                            {
                                                "grouped": [
                                                    {
                                                        "noteType": "Normal",
                                                        "base": "B",
                                                        "liquescent": false,
                                                        "octave": 4,
                                                        "focus": false,
                                                        "uuid": "85bba922-f33c-4ce2-95d6-eb22fe3badc6"
                                                    },
                                                    {
                                                        "noteType": "Normal",
                                                        "base": "C",
                                                        "liquescent": false,
                                                        "octave": 5,
                                                        "focus": false,
                                                        "uuid": "c9a069c7-456e-4151-8766-9d7caad53e07"
                                                    }
                                                ]
                                            },
                                            {
                                                "grouped": [
                                                    {
                                                        "noteType": "Normal",
                                                        "base": "A",
                                                        "liquescent": false,
                                                        "octave": 4,
                                                        "focus": false,
                                                        "uuid": "aa7ac4eb-c358-4ceb-8bce-5d3a2ef407e0"
                                                    }
                                                ]
                                            },
                                            {
                                                "grouped": [
                                                    {
                                                        "noteType": "Normal",
                                                        "base": "G",
                                                        "liquescent": false,
                                                        "octave": 4,
                                                        "focus": false,
                                                        "uuid": "97a42b45-7e60-4313-ba26-44a91a1f805d"
                                                    }
                                                ]
                                            },
                                            {
                                                "grouped": [
                                                    {
                                                        "noteType": "Normal",
                                                        "base": "A",
                                                        "liquescent": false,
                                                        "octave": 4,
                                                        "focus": false,
                                                        "uuid": "427af7e0-2584-4fbe-aed8-e8a221fc15c4"
                                                    },
                                                    {
                                                        "noteType": "Normal",
                                                        "base": "C",
                                                        "liquescent": false,
                                                        "octave": 5,
                                                        "focus": false,
                                                        "uuid": "0ecf673f-aaeb-47df-930a-ce76b2808db6"
                                                    }
                                                ]
                                            },
                                            {
                                                "grouped": [
                                                    {
                                                        "noteType": "Normal",
                                                        "base": "G",
                                                        "liquescent": false,
                                                        "octave": 4,
                                                        "focus": false,
                                                        "uuid": "818f3348-defd-4991-8ca7-c8d6d515ce14"
                                                    }
                                                ]
                                            },
                                            {
                                                "grouped": [
                                                    {
                                                        "noteType": "Normal",
                                                        "base": "F",
                                                        "liquescent": false,
                                                        "octave": 4,
                                                        "focus": false,
                                                        "uuid": "b7b8e10f-56d3-4af1-a5a4-3a81870304c0"
                                                    }
                                                ]
                                            },
                                            {
                                                "grouped": [
                                                    {
                                                        "noteType": "Normal",
                                                        "base": "F",
                                                        "liquescent": false,
                                                        "octave": 4,
                                                        "focus": false,
                                                        "uuid": "0021682c-74c7-42fe-b27a-abe40ffbf29a"
                                                    }
                                                ]
                                            },
                                            {
                                                "grouped": [
                                                    {
                                                        "noteType": "Normal",
                                                        "base": "G",
                                                        "liquescent": false,
                                                        "octave": 4,
                                                        "focus": false,
                                                        "uuid": "7d223fb4-137e-4d6d-8f5c-41c4425bb21d"
                                                    },
                                                    {
                                                        "noteType": "Normal",
                                                        "base": "A",
                                                        "liquescent": false,
                                                        "octave": 4,
                                                        "focus": false,
                                                        "uuid": "a655abdf-5e2f-4646-9360-3ad7c45eff31"
                                                    },
                                                    {
                                                        "noteType": "Normal",
                                                        "base": "G",
                                                        "liquescent": false,
                                                        "octave": 4,
                                                        "focus": false,
                                                        "uuid": "3c988071-70a6-4db1-91d8-76f9ee6a3737"
                                                    }
                                                ]
                                            }
                                        ]
                                    },
                                    {
                                        "nonSpaced": [
                                            {
                                                "grouped": [
                                                    {
                                                        "noteType": "Normal",
                                                        "base": "A",
                                                        "liquescent": false,
                                                        "octave": 4,
                                                        "focus": false,
                                                        "uuid": "49f5f4cc-ba33-44ea-9c57-39082f0f8822"
                                                    }
                                                ]
                                            },
                                            {
                                                "grouped": [
                                                    {
                                                        "noteType": "Normal",
                                                        "base": "C",
                                                        "liquescent": false,
                                                        "octave": 5,
                                                        "focus": false,
                                                        "uuid": "62ac7170-f5b4-4d8b-a538-eca25512cec0"
                                                    },
                                                    {
                                                        "noteType": "Normal",
                                                        "base": "A",
                                                        "liquescent": false,
                                                        "octave": 4,
                                                        "focus": false,
                                                        "uuid": "9a61e417-b36d-47d2-9798-cb6682b499bb"
                                                    }
                                                ]
                                            },
                                            {
                                                "grouped": [
                                                    {
                                                        "noteType": "Normal",
                                                        "base": "A",
                                                        "liquescent": false,
                                                        "octave": 4,
                                                        "focus": false,
                                                        "uuid": "47ee891d-1fef-4b16-8dd7-12ae6ac6844b"
                                                    }
                                                ]
                                            },
                                            {
                                                "grouped": [
                                                    {
                                                        "noteType": "Normal",
                                                        "base": "F",
                                                        "liquescent": false,
                                                        "octave": 4,
                                                        "focus": false,
                                                        "uuid": "9dae2675-50f7-4432-99ac-20649d3635b0"
                                                    },
                                                    {
                                                        "noteType": "Normal",
                                                        "base": "G",
                                                        "liquescent": false,
                                                        "octave": 4,
                                                        "focus": false,
                                                        "uuid": "6c1e2cc1-1bcf-4204-bb53-470ee245abdb"
                                                    },
                                                    {
                                                        "noteType": "Normal",
                                                        "base": "F",
                                                        "liquescent": false,
                                                        "octave": 4,
                                                        "focus": false,
                                                        "uuid": "eae0f8e7-abab-4dd1-86c6-f4b40bf1c614"
                                                    }
                                                ]
                                            }
                                        ]
                                    }
                                ]
                            },
                            "syllableType": "Normal"
                        }
                    ]
                },
                {
                    "kind": "ZeileContainer",
                    "uuid": "4671b768-184e-489e-b18b-20b6552aa934",
                    "children": []
                }
            ],
            "data": [
                {
                    "name": "Signatur",
                    "data": ""
                }
            ]
        }
    ],
    "comments": [],
    "documentType": "Level1"
}